{
  "fetched_at": "2026-07-02T14:27:47.955Z",
  "source_timestamp": "07/01/2026 07:35",
  "bytes": 62955,
  "sources": {
    "musiclist_txt": {
      "ok": true,
      "count": 410,
      "strategy": "snapshot-fallback",
      "last_ok": "2026-07-02T14:27:44.659Z",
      "last_attempt": "2026-07-02T14:27:44.659Z",
      "error": null
    },
    "tribe_ics": {
      "ok": true,
      "count": 35,
      "strategy": "live",
      "last_ok": "2026-07-02T14:27:45.009Z",
      "last_attempt": "2026-07-02T14:27:45.009Z",
      "error": null
    },
    "talent_club": {
      "ok": true,
      "count": 1,
      "strategy": "live",
      "last_ok": "2026-07-02T14:27:46.011Z",
      "last_attempt": "2026-07-02T14:27:46.011Z",
      "error": null
    },
    "black_sheep": {
      "ok": true,
      "count": 7,
      "strategy": "live",
      "last_ok": "2026-07-02T14:27:46.411Z",
      "last_attempt": "2026-07-02T14:27:46.411Z",
      "error": null
    },
    "sou_localist": {
      "ok": true,
      "count": 0,
      "strategy": "live",
      "last_ok": "2026-07-02T14:27:46.538Z",
      "last_attempt": "2026-07-02T14:27:46.538Z",
      "error": null
    },
    "ashland_city": {
      "ok": true,
      "count": 3,
      "strategy": "live",
      "last_ok": "2026-07-02T14:27:47.421Z",
      "last_attempt": "2026-07-02T14:27:47.421Z",
      "error": null
    }
  },
  "event_count": 434,
  "venue_count": 314,
  "deduped": 22,
  "content_hash": "9fe50a3de4fd5dab"
}
