{
  "fetched_at": "2026-07-17T21:06:47.243Z",
  "source_timestamp": "07/17/2026 11:53",
  "bytes": 57127,
  "sources": {
    "musiclist_txt": {
      "ok": true,
      "count": 318,
      "strategy": "snapshot-fallback",
      "last_ok": "2026-07-17T21:06:42.621Z",
      "last_attempt": "2026-07-17T21:06:42.621Z",
      "error": null
    },
    "tribe_ics": {
      "ok": true,
      "count": 25,
      "strategy": "live",
      "last_ok": "2026-07-17T21:06:42.908Z",
      "last_attempt": "2026-07-17T21:06:42.908Z",
      "error": null
    },
    "talent_club": {
      "ok": true,
      "count": 7,
      "strategy": "live",
      "last_ok": "2026-07-17T21:06:45.521Z",
      "last_attempt": "2026-07-17T21:06:45.521Z",
      "error": null
    },
    "black_sheep": {
      "ok": true,
      "count": 7,
      "strategy": "live",
      "last_ok": "2026-07-17T21:06:45.867Z",
      "last_attempt": "2026-07-17T21:06:45.867Z",
      "error": null
    },
    "sou_localist": {
      "ok": true,
      "count": 0,
      "strategy": "live",
      "last_ok": "2026-07-17T21:06:46.052Z",
      "last_attempt": "2026-07-17T21:06:46.052Z",
      "error": null
    },
    "ashland_city": {
      "ok": true,
      "count": 4,
      "strategy": "live",
      "last_ok": "2026-07-17T21:06:46.798Z",
      "last_attempt": "2026-07-17T21:06:46.798Z",
      "error": null
    }
  },
  "event_count": 350,
  "venue_count": 319,
  "deduped": 11,
  "content_hash": "7c6433df41803313"
}
